dashamail/__init__.py
dashamail/client.py
dashamail/exceptions.py
dashamail-0.1.0.dist-info/LICENSE
dashamail-0.1.0.dist-info/METADATA
dashamail-0.1.0.dist-info/WHEEL
dashamail-0.1.0.dist-info/top_level.txt
dashamail-0.1.0.dist-info/RECORD
