Metadata-Version: 2.1
Name: dashamail
Version: 0.1.0
Summary: DashaMail API client for Python
Home-page: https://github.com/pilosus/python-dashamail/
Author: Vitaly Samigullin
Author-email: vrs@pilosus.org
License: Apache License 2.0
Platform: UNKNOWN
Classifier: Development Status :: 4 - Beta
Classifier: Programming Language :: Python :: 3
Classifier: Intended Audience :: Developers
Classifier: License :: OSI Approved :: Apache Software License
Classifier: Topic :: Office/Business
Requires-Python: >=3.6,<4
License-File: LICENSE
Requires-Dist: requests (<3,>=2.0)
